sciveo
