Metadata-Version: 2.1
Name: sciveo
Version: 0.1.90
Provides-Extra: mon
Provides-Extra: net
Provides-Extra: server
Provides-Extra: media
Provides-Extra: media-ml
Provides-Extra: web
Provides-Extra: db
Provides-Extra: power
Provides-Extra: all
Provides-Extra: ml
